reportutil/__init__.py
reportutil/_config.py
reportutil/_constants.py
reportutil/_exceptions.py
reportutil/_metadata.py
reportutil/report.py
reportutil/components/__init__.py
reportutil/components/dir.py
reportutil/components/file.py
reportutil/components/node.py
reportutil/nodes/__init__.py
reportutil/nodes/html.py
reportutil/resources/__init__.py
reportutil/resources/schema/__init__.py
reportutil/resources/schema/reports.json
reportutil/resources/templates/__init__.py
reportutil/resources/templates/reports.json
reportutil/unittests/__init__.py
reportutil/unittests/test_reportutil.py
reportutil-0.0.6.dist-info/LICENSE.txt
reportutil-0.0.6.dist-info/METADATA
reportutil-0.0.6.dist-info/RECORD
reportutil-0.0.6.dist-info/WHEEL
reportutil-0.0.6.dist-info/entry_points.txt
reportutil-0.0.6.dist-info/top_level.txt
