Metadata-Version: 2.1
Name: reportutil
Version: 0.0.6
Summary: Module to assist in the creation of reports.
Home-page: https://bitbucket.org/davisowb/reportutil.git
Author: Oli Davis
Author-email: oli.davis@me.com
License: MIT
Download-URL: https://bitbucket.org/davisowb/reportutil.git/get/0.0.6.tar
Keywords: report,html
Platform: UNKNOWN
Classifier: Development Status :: 3 - Alpha
Classifier: Intended Audience :: Developers
Classifier: License :: OSI Approved :: MIT License
Classifier: Programming Language :: Python :: 2
Classifier: Programming Language :: Python :: 2.7
Classifier: Programming Language :: Python :: 3
Classifier: Programming Language :: Python :: 3.6
Classifier: Topic :: Utilities
Provides-Extra: test
Requires-Dist: pip (>=9.0.1)
Requires-Dist: future (>=0.16.0)
Requires-Dist: attrs (>=16.3.0)
Requires-Dist: dominate (>=2.3.1)
Requires-Dist: configurationutil (>=1.5.5)
Requires-Dist: logging-helper (>=1.5.0)
Requires-Dist: fdutil (>=1.6.0)
Provides-Extra: test
